src/.DS_Store
src/data_pipeline/__init__.py
src/data_pipeline/feature_engineering/__init__.py
src/data_pipeline/feature_engineering/key_smash.py
src/data_pipeline/feature_engineering/word_embedding.py
src/data_pipeline/pre_processing/__init__.py
src/data_pipeline/pre_processing/concatenate_columns.py
src/main.py
src/parser/YAML_parser.py
src/parser/__init__.py
src/parser/const.py
src/parser/feature_engineering_parser.py
src/parser/model_parser.py
src/parser/parser_base.py
src/yamls/basic_example.yaml
tests/.DS_Store
tests/__init__.py
tests/data_pipeline/.DS_Store
tests/data_pipeline/__init__.py
tests/mock/.DS_Store
tests/mock/data_mock.csv
tests/mock/fail/.DS_Store
tests/mock/success/.DS_Store
tests/parser/.DS_Store
tests/parser/__init__.py
tests/test_placeholder.py
tf_gces-0.1.5.dist-info/METADATA
tf_gces-0.1.5.dist-info/WHEEL
tf_gces-0.1.5.dist-info/LICENSE
tf_gces-0.1.5.dist-info/RECORD
